langfarm/__init__.py
langfarm/hooks/__init__.py
langfarm/hooks/dashscope/__init__.py
langfarm/hooks/dashscope/generation.py
langfarm/hooks/langfuse/__init__.py
langfarm/hooks/langfuse/callback/__init__.py
langfarm/hooks/langfuse/callback/langchain.py
langfarm-0.1.2.dist-info/LICENSE
langfarm-0.1.2.dist-info/METADATA
langfarm-0.1.2.dist-info/WHEEL
langfarm-0.1.2.dist-info/RECORD
