Metadata-Version: 2.1
Name: langfarm
Version: 0.1.2
Summary: LLM 相关工具集
License: MIT
Author: chenlb
Author-email: chenlbphoto@163.com
Requires-Python: >=3.9,<4.0
Classifier: License :: OSI Approved :: MIT License
Classifier: Programming Language :: Python :: 3
Classifier: Programming Language :: Python :: 3.9
Classifier: Programming Language :: Python :: 3.10
Classifier: Programming Language :: Python :: 3.11
Classifier: Programming Language :: Python :: 3.12
Classifier: Programming Language :: Python :: 3.13
Requires-Dist: langfuse (>=2.53.9,<3.0.0)
